{
    "patient_id": "ISPY2_519738",
    "clinical_data": {
        "age": 58,
        "menopausal_status": "post",
        "breast_density": ""
    },
    "primary_lesion": {
        "pcr": 1,
        "tumor_subtype": "her2_enriched",
        "breast_coordinates": {
            "x_min": 1,
            "x_max": 78,
            "y_min": 1,
            "y_max": 229,
            "z_min": 3,
            "z_max": 254
        }
    },
    "imaging_data": {
        "bilateral": false,
        "dataset": "ISPY2",
        "site": "AAO",
        "scanner_manufacturer": "GE",
        "scanner_model": "Signa HDxt",
        "field_strength": 1.5,
        "echo_time": 2.696,
        "repetition_time": 6.568
    }
}